datacards/__init__.py
datacards/card.py
datacards/files.py
datacards/main.py
datacards/parse.py
datacards/types.py
datacards/utils.py
datacards-0.1.1.dist-info/entry_points.txt
datacards-0.1.1.dist-info/WHEEL
datacards-0.1.1.dist-info/METADATA
datacards-0.1.1.dist-info/RECORD
