Metadata-Version: 2.1
Name: datacards
Version: 0.1.1
Summary: Append missing model cards to Huggingface datasets
Home-page: https://github.com/Hugging-Face-Supporter/datacards
License: Apache-2.0
Keywords: huggingface,transformers,datasets,dataset,text,modelcard,card
Author: MarkusSagen
Author-email: markus.john.sagen@gmail.com
Requires-Python: >=3.8,<4.0
Classifier: License :: OSI Approved :: Apache Software License
Classifier: Programming Language :: Python :: 3
Classifier: Programming Language :: Python :: 3.10
Classifier: Programming Language :: Python :: 3.8
Classifier: Programming Language :: Python :: 3.9
Requires-Dist: PyYAML (>=6.0,<7.0)
Requires-Dist: datasets (>=1.14.0,<2.0.0)
Requires-Dist: pydantic (>=1.8.0,<2.0.0)
Requires-Dist: rich[jupyter] (>=10.14.0,<11.0.0)
Project-URL: Repository, https://github.com/Hugging-Face-Supporter/datacards
